<step title="BackgroundTrace" date="2026-06-21T10:37:56.202" instance="7c92b7" url="/api/zipdeploy" method="POST" >
  <step title="Creating temporary deployment - FetchDeploymentManager" date="2026-06-21T10:37:56.247" /><!-- duration: 2ms -->
  <step title="Creating temporary deployment" date="2026-06-21T10:37:56.254" /><!-- duration: 46ms -->
  <step title="Performing fetch based deployment" date="2026-06-21T10:37:56.387" >
    <step title="Cleaning up temp folders from previous zip deployments and extracting pushed zip file /tmp/zipdeploy/d26c4fe4-0f95-4b02-924a-492f346b54b5.zip (3.60 MB) to /tmp/zipdeploy/extracted" date="2026-06-21T10:37:57.595" >
      <step title="ChmodRecursive Process exited with total time taken in ms: 36" date="2026-06-21T10:37:57.947" /><!-- duration: 3ms -->
    </step><!-- duration: 360ms -->
    <step title="Deployment timer started" date="2026-06-21T10:37:59.975" >
      <step title="DeploymentManager.Deploy(id:08ed15cf-aa18-4351-aed5-dbc8f9f10946)" date="2026-06-21T10:37:59.979" >
        <step title="Collecting changeset information" date="2026-06-21T10:38:00.027" /><!-- duration: 175ms -->
        <step title="Updating submodules" date="2026-06-21T10:38:00.207" /><!-- duration: 1188ms -->
        <step title="Determining deployment builder" date="2026-06-21T10:38:01.780" >
          <step title="Builder is BasicBuilder" date="2026-06-21T10:38:01.822" /><!-- duration: 48ms -->
        </step><!-- duration: 110ms -->
        <step title="PreDeployment: context.CleanOutputPath False" date="2026-06-21T10:38:02.032" >
          <step title="PreDeployment: context.OutputPath /home/site/wwwroot" date="2026-06-21T10:38:02.281" >
            <step title="Building" date="2026-06-21T10:38:02.577" >
              <step title="Executing external process" date="2026-06-21T10:38:02.975" type="process" path="starter.sh" arguments="/opt/Kudu/Scripts/parallel_rsync.sh /tmp/zipdeploy/extracted /home/site/wwwroot 8 /tmp/ False True  " /><!-- duration: 2991ms -->
              <step title="Triggering recycle (preview mode disabled)." date="2026-06-21T10:38:06.444" /><!-- duration: 27ms -->
              <step title="Modified file to trigger a restart of the app container." date="2026-06-21T10:38:06.572" /><!-- duration: 27ms -->
              <step title="Skip function trigger and logicapp sync because function is not enabled." date="2026-06-21T10:38:06.629" /><!-- duration: 59ms -->
              <step title="Purge deployment items" date="2026-06-21T10:38:08.071" >
                <step title="Remove 96254d63-, Success, received at 06/20/2026 22:02:21" date="2026-06-21T10:38:08.140" /><!-- duration: 3ms -->
              </step><!-- duration: 77ms -->
            </step><!-- duration: 5660ms -->
          </step><!-- duration: 5968ms -->
          <step title="Cleaning up temp files" date="2026-06-21T10:38:08.252" /><!-- duration: 5ms -->
          <step title="Cleaning up temp files" date="2026-06-21T10:38:08.262" /><!-- duration: 518ms -->
          <step title="Reloading status file with latest updates" date="2026-06-21T10:38:08.818" >
            <step title="WebHooksManager.PublishEventAsync: PostDeployment" date="2026-06-21T10:38:08.822" /><!-- duration: 35ms -->
          </step><!-- duration: 42ms -->
          <step title="Cleaning up temporary deployment - fetch deployment was successful" date="2026-06-21T10:38:08.866" /><!-- duration: 3ms -->
        </step><!-- duration: 6910ms -->
      </step><!-- duration: 8995ms -->
